Metadata-Version: 2.1
Name: generador-aleatorio-231dsad127db
Version: 0.1.0
Summary: El generador aleatorio de frases mas potente del mundo! No hay otro igual...tiembla Google!
License: MIT
Author: internetmosquito
Author-email: alejandrovillamarin@gmail.com
Requires-Python: >=3.9,<4.0
Classifier: License :: OSI Approved :: MIT License
Classifier: Programming Language :: Python :: 3
Classifier: Programming Language :: Python :: 3.9
